{
  "project_info": {
    "project_number": "886852930120",
    "firebase_url": "https://taxi-app-c22e2.firebaseio.com",
    "project_id": "taxi-app-c22e2",
    "storage_bucket": "taxi-app-c22e2.appspot.com"
  },
  "client": [
    {
      "client_info": {
        "mobilesdk_app_id": "1:886852930120:android:9b391f1bc37987ebeca67d",
        "android_client_info": {
          "package_name": "ru.mvlikhachev.texiapp"
        }
      },
      "oauth_client": [
        {
          "client_id": "886852930120-vluqm7cpkultcckv0edsb655hh98eugn.apps.googleusercontent.com",
          "client_type": 1,
          "android_info": {
            "package_name": "ru.mvlikhachev.texiapp",
            "certificate_hash": "84488f1e5bad17827f76795680302581b367b4e6"
          }
        },
        {
          "client_id": "886852930120-d3unlhp0gsmaiq8ndff885s7chfseffs.apps.googleusercontent.com",
          "client_type": 3
        }
      ],
      "api_key": [
        {
          "current_key": "AIzaSyD6rISKAZTpoa77tzp4ATW4HTHHiN1iIOw"
        }
      ],
      "services": {
        "appinvite_service": {
          "other_platform_oauth_client": [
            {
              "client_id": "886852930120-d3unlhp0gsmaiq8ndff885s7chfseffs.apps.googleusercontent.com",
              "client_type": 3
            }
          ]
        }
      }
    }
  ],
  "configuration_version": "1"
}